{
	"to_universal": {
		"map_properties": {
			"block_data": {
				"0": {
					"new_block": "universal_minecraft:plant",
					"new_properties": {
						"type": "dead_bush"
					}
				}
			}
		}
	},
	"from_universal": {
		"universal_minecraft:plant": {
			"map_properties": {
				"type": {
					"dead_bush": {
						"new_block": "minecraft:deadbush",
						"new_properties": {
							"block_data": "0"
						}
					}
				}
			}
		}
	},
	"blockstate_to_universal": {
		"new_block": "universal_minecraft:plant",
		"new_properties": {
			"type": "dead_bush"
		}
	},
	"blockstate_from_universal": {
		"universal_minecraft:plant": {
			"map_properties": {
				"type": {
					"dead_bush": {
						"new_block": "minecraft:deadbush"
					}
				}
			}
		}
	}
}