{
    "to_universal": [
        {
            "function": "new_block",
            "options": "universal_minecraft:planks"
        },
        {
            "function": "new_properties",
            "options": {
                "material": "\"jungle\""
            }
        }
    ],
    "from_universal": {
        "universal_minecraft:planks": [
            {
                "function": "new_block",
                "options": "minecraft:oak_planks"
            },
            {
                "function": "map_properties",
                "options": {
                    "material": {
                        "\"jungle\"": [
                            {
                                "function": "new_block",
                                "options": "minecraft:jungle_planks"
                            }
                        ]
                    }
                }
            }
        ]
    }
}