{
	"remove": [
		"oak_wood",
		"stripped_oak_wood",
		"spruce_wood",
		"stripped_spruce_wood",
		"birch_wood",
		"stripped_birch_wood",
		"jungle_wood",
		"stripped_jungle_wood",
		"acacia_wood",
		"stripped_acacia_wood",
		"dark_oak_wood",
		"stripped_dark_oak_wood",
		"crimson_hyphae",
		"stripped_crimson_hyphae",
		"warped_hyphae",
		"stripped_warped_hyphae",
		"mangrove_wood",
		"stripped_mangrove_wood",
		"cherry_wood",
		"stripped_cherry_wood",
		"pale_oak_wood",
		"stripped_pale_oak_wood"
	],
	"add": {
		"wood": {
			"properties": {
				"material": [
					"\"oak\"",
					"\"spruce\"",
					"\"birch\"",
					"\"jungle\"",
					"\"acacia\"",
					"\"dark_oak\"",
					"\"mangrove\"",
					"\"crimson\"",
					"\"warped\"",
					"\"cherry\"",
					"\"pale_oak\""
				],
				"axis": [
					"\"x\"",
					"\"y\"",
					"\"z\""
				],
				"stripped": [
					"\"false\"",
					"\"true\""
				]
			},
			"defaults": {
				"material": "\"oak\"",
				"axis": "\"y\"",
				"stripped": "\"false\""
			}
		}
	}
}