{
    "to_universal": [
        {
            "function": "new_block",
            "options": "universal_minecraft:sponge"
        },
        {
            "function": "new_properties",
            "options": {
                "wet": "\"false\""
            }
        }
    ],
    "from_universal": {
        "universal_minecraft:sponge": [
            {
                "function": "new_block",
                "options": "minecraft:sponge"
            },
            {
                "function": "map_properties",
                "options": {
                    "wet": {
                        "\"false\"": [
                            {
                                "function": "new_block",
                                "options": "minecraft:sponge"
                            }
                        ]
                    }
                }
            }
        ]
    }
}