{
	"remove": [
		"oak_stairs",
		"spruce_stairs",
		"birch_stairs",
		"jungle_stairs",
		"acacia_stairs",
		"dark_oak_stairs",
		"brick_stairs",
		"cobblestone_stairs",
		"stone_brick_stairs",
		"sandstone_stairs",
		"red_sandstone_stairs",
		"nether_brick_stairs",
		"quartz_stairs",
		"purpur_stairs",
		"prismarine_stairs",
		"prismarine_brick_stairs",
		"dark_prismarine_stairs",
		"andesite_stairs",
		"diorite_stairs",
		"end_stone_brick_stairs",
		"granite_stairs",
		"mossy_cobblestone_stairs",
		"mossy_stone_brick_stairs",
		"polished_andesite_stairs",
		"polished_diorite_stairs",
		"polished_granite_stairs",
		"red_nether_brick_stairs",
		"smooth_quartz_stairs",
		"smooth_red_sandstone_stairs",
		"smooth_sandstone_stairs",
		"stone_stairs",
		"crimson_stairs",
		"warped_stairs",
		"blackstone_stairs",
		"polished_blackstone_brick_stairs",
		"polished_blackstone_stairs",
		"oxidized_cut_copper_stairs",
		"weathered_cut_copper_stairs",
		"exposed_cut_copper_stairs",
		"cut_copper_stairs",
		"waxed_oxidized_cut_copper_stairs",
		"waxed_weathered_cut_copper_stairs",
		"waxed_exposed_cut_copper_stairs",
		"waxed_cut_copper_stairs",
		"cobbled_deepslate_stairs",
		"polished_deepslate_stairs",
		"deepslate_tile_stairs",
		"deepslate_brick_stairs",
		"mangrove_stairs",
		"mud_brick_stairs",
		"bamboo_stairs",
		"bamboo_mosaic_stairs"
	],
	"add": {
		"stairs": {
			"properties": {
				"material": [
					"\"oak\"",
					"\"spruce\"",
					"\"birch\"",
					"\"jungle\"",
					"\"acacia\"",
					"\"dark_oak\"",
					"\"mangrove\"",
					"\"brick\"",
					"\"cobblestone\"",
					"\"stone_brick\"",
					"\"sandstone\"",
					"\"red_sandstone\"",
					"\"nether_brick\"",
					"\"quartz\"",
					"\"purpur\"",
					"\"prismarine\"",
					"\"prismarine_brick\"",
					"\"dark_prismarine\"",
					"\"andesite\"",
					"\"diorite\"",
					"\"end_stone_brick\"",
					"\"granite\"",
					"\"mossy_cobblestone\"",
					"\"mossy_stone_brick\"",
					"\"polished_andesite\"",
					"\"polished_diorite\"",
					"\"polished_granite\"",
					"\"red_nether_brick\"",
					"\"smooth_quartz\"",
					"\"smooth_red_sandstone\"",
					"\"smooth_sandstone\"",
					"\"stone\"",
					"\"crimson\"",
					"\"warped\"",
					"\"blackstone\"",
					"\"polished_blackstone_brick\"",
					"\"polished_blackstone\"",
					"\"oxidized_cut_copper\"",
					"\"weathered_cut_copper\"",
					"\"exposed_cut_copper\"",
					"\"cut_copper\"",
					"\"waxed_oxidized_cut_copper\"",
					"\"waxed_weathered_cut_copper\"",
					"\"waxed_exposed_cut_copper\"",
					"\"waxed_cut_copper\"",
					"\"cobbled_deepslate\"",
					"\"polished_deepslate\"",
					"\"deepslate_tile\"",
					"\"deepslate_brick\"",
					"\"mud_brick\"",
					"\"bamboo\"",
					"\"bamboo_mosaic\""
				],
				"facing": [
					"\"north\"",
					"\"south\"",
					"\"west\"",
					"\"east\""
				],
				"half": [
					"\"top\"",
					"\"bottom\""
				],
				"shape": [
					"\"straight\"",
					"\"inner_left\"",
					"\"inner_right\"",
					"\"outer_left\"",
					"\"outer_right\""
				]
			},
			"defaults": {
				"material": "\"oak\"",
				"facing": "\"north\"",
				"half": "\"bottom\"",
				"shape": "\"straight\""
			}
		}
	}
}