{
    "map_properties": {
        "block_data": {
            "0": {
                "new_block": "minecraft:leaves",
                "new_properties": {
                    "block": "oak",
                    "decayable": "true",
                    "check_decay": "false"
                }
            },
            "1": {
                "new_block": "minecraft:leaves",
                "new_properties": {
                    "block": "spruce",
                    "decayable": "true",
                    "check_decay": "false"
                }
            },
            "2": {
                "new_block": "minecraft:leaves",
                "new_properties": {
                    "block": "birch",
                    "decayable": "true",
                    "check_decay": "false"
                }
            },
            "3": {
                "new_block": "minecraft:leaves",
                "new_properties": {
                    "block": "jungle",
                    "decayable": "true",
                    "check_decay": "false"
                }
            },
            "4": {
                "new_block": "minecraft:leaves",
                "new_properties": {
                    "block": "oak",
                    "decayable": "false",
                    "check_decay": "false"
                }
            },
            "5": {
                "new_block": "minecraft:leaves",
                "new_properties": {
                    "block": "spruce",
                    "decayable": "false",
                    "check_decay": "false"
                }
            },
            "6": {
                "new_block": "minecraft:leaves",
                "new_properties": {
                    "block": "birch",
                    "decayable": "false",
                    "check_decay": "false"
                }
            },
            "7": {
                "new_block": "minecraft:leaves",
                "new_properties": {
                    "block": "jungle",
                    "decayable": "false",
                    "check_decay": "false"
                }
            },
            "8": {
                "new_block": "minecraft:leaves",
                "new_properties": {
                    "block": "oak",
                    "decayable": "true",
                    "check_decay": "true"
                }
            },
            "9": {
                "new_block": "minecraft:leaves",
                "new_properties": {
                    "block": "spruce",
                    "decayable": "true",
                    "check_decay": "true"
                }
            },
            "10": {
                "new_block": "minecraft:leaves",
                "new_properties": {
                    "block": "birch",
                    "decayable": "true",
                    "check_decay": "true"
                }
            },
            "11": {
                "new_block": "minecraft:leaves",
                "new_properties": {
                    "block": "jungle",
                    "decayable": "true",
                    "check_decay": "true"
                }
            },
            "12": {
                "new_block": "minecraft:leaves",
                "new_properties": {
                    "block": "oak",
                    "decayable": "false",
                    "check_decay": "true"
                }
            },
            "13": {
                "new_block": "minecraft:leaves",
                "new_properties": {
                    "block": "spruce",
                    "decayable": "false",
                    "check_decay": "true"
                }
            },
            "14": {
                "new_block": "minecraft:leaves",
                "new_properties": {
                    "block": "birch",
                    "decayable": "false",
                    "check_decay": "true"
                }
            },
            "15": {
                "new_block": "minecraft:leaves",
                "new_properties": {
                    "block": "jungle",
                    "decayable": "false",
                    "check_decay": "true"
                }
            }
        }
    }
}