{
    "to_universal": [
        {
            "function": "new_block",
            "options": "universal_minecraft:stained_terracotta"
        },
        {
			"function": "new_properties",
			"options": {
				"color": "\"purple\""
			}
		}
    ],
    "from_universal": {
        "universal_minecraft:stained_terracotta": [
            {
                "function": "new_block",
                "options": "minecraft:white_terracotta"
            },
            {
                "function": "map_properties",
                "options": {
                    "color": {
                        "\"purple\"": [
                            {
								"function": "new_block",
								"options": "minecraft:purple_terracotta"
							}
                        ]
                    }
                }
            }
        ]
    }
}