{
    "minecraft:bamboo_block": {
        "block_added": {
            "defaults": {
                "pillar_axis": "\"y\""
            },
            "properties": {
                "pillar_axis": [
                    "\"y\"",
                    "\"x\"",
                    "\"z\""
                ]
            }
        }
    },
    "minecraft:chiseled_bookshelf": {
        "properties_removed": {
            "last_interacted_slot": [
                "0",
                "1",
                "2",
                "3",
                "4",
                "5",
                "6"
            ]
        },
        "values_added": {
            "books_stored": [
                "57",
                "46",
                "13",
                "38",
                "45",
                "18",
                "39",
                "55",
                "56",
                "22",
                "37",
                "11",
                "28",
                "26",
                "58",
                "53",
                "20",
                "51",
                "34",
                "43",
                "33",
                "10",
                "21",
                "27",
                "14",
                "35",
                "42",
                "32",
                "15",
                "30",
                "60",
                "23",
                "25",
                "17",
                "63",
                "19",
                "47",
                "41",
                "59",
                "24",
                "40",
                "62",
                "29",
                "36",
                "54",
                "16",
                "52",
                "31",
                "9",
                "8",
                "49",
                "50",
                "61",
                "48",
                "44",
                "7",
                "12"
            ]
        }
    },
    "minecraft:stripped_bamboo_block": {
        "block_added": {
            "defaults": {
                "pillar_axis": "\"y\""
            },
            "properties": {
                "pillar_axis": [
                    "\"y\"",
                    "\"x\"",
                    "\"z\""
                ]
            }
        }
    }
}